flask_batteries_included/__init__.py
flask_batteries_included/autoapp.py
flask_batteries_included/blueprint_debug/__init__.py
flask_batteries_included/blueprint_monitoring/__init__.py
flask_batteries_included/config.py
flask_batteries_included/helpers/__init__.py
flask_batteries_included/helpers/apispec.py
flask_batteries_included/helpers/converters.py
flask_batteries_included/helpers/error_handler.py
flask_batteries_included/helpers/etags.py
flask_batteries_included/helpers/json.py
flask_batteries_included/helpers/metrics.py
flask_batteries_included/helpers/request_arg.py
flask_batteries_included/helpers/request_id.py
flask_batteries_included/helpers/routes.py
flask_batteries_included/helpers/schema.py
flask_batteries_included/helpers/security/__init__.py
flask_batteries_included/helpers/security/connexion_bearerinfo.py
flask_batteries_included/helpers/security/endpoint_security.py
flask_batteries_included/helpers/security/jwk.py
flask_batteries_included/helpers/security/jwt.py
flask_batteries_included/helpers/security/jwt_parsers.py
flask_batteries_included/helpers/timestamp.py
flask_batteries_included/helpers/unittest_mode.py
flask_batteries_included/py.typed
flask_batteries_included/sqldb.py
flask_batteries_included-3.1.2.dist-info/LICENSE.md
flask_batteries_included-3.1.2.dist-info/WHEEL
flask_batteries_included-3.1.2.dist-info/METADATA
flask_batteries_included-3.1.2.dist-info/RECORD
