Metadata-Version: 2.1
Name: flask-batteries-included
Version: 3.1.2
Summary: Batteries-included library for Polaris microservices using Flask
Home-page: https://github.com/polaris-foundation/flask-batteries-included
Keywords: Polaris,Flask
Author: Rob Grant
Author-email: rob.grant@sensynehealth.com
Requires-Python: >=3.8,<4.0
Classifier: Programming Language :: Python :: 3
Classifier: Programming Language :: Python :: 3.10
Classifier: Programming Language :: Python :: 3.8
Classifier: Programming Language :: Python :: 3.9
Provides-Extra: apispec
Provides-Extra: pgsql
Requires-Dist: Flask (>=2.0.0,<3.0.0)
Requires-Dist: Flask-Log-Request-Id (<1.0.0)
Requires-Dist: Flask-Migrate (>=3.0.0,<4.0.0); extra == "pgsql"
Requires-Dist: Flask-SQLAlchemy (>=2.0.0,<3.0.0); extra == "pgsql"
Requires-Dist: apispec (>=5.0.0,<6.0.0)
Requires-Dist: apispec-webframeworks (<1.0.0); extra == "apispec"
Requires-Dist: connexion[swagger-ui] (>=2.0.0,<3.0.0); extra == "apispec"
Requires-Dist: dhos-redis (>=1.0.0,<2.0.0)
Requires-Dist: environs (>=9.0.0,<10.0.0)
Requires-Dist: healthcheck (>=1.0.0,<2.0.0)
Requires-Dist: marshmallow (>=3.0.0,<4.0.0)
Requires-Dist: prometheus-client (<1.0.0)
Requires-Dist: psycopg2-binary (>=2.0.0,<3.0.0); extra == "pgsql"
Requires-Dist: python-jose (>=3.0.0,<4.0.0)
Requires-Dist: requests (>=2.0.0,<3.0.0)
Requires-Dist: she-logging (>=1.0.0,<2.0.0)
Requires-Dist: waitress (>=2.0.0,<3.0.0)
Project-URL: Repository, https://github.com/polaris-foundation/flask-batteries-included
